[
    {"name": "dorothea",                  "id": 0,  "size": "medium", "sparse": true},
    {"name": "secom",                     "id": 1,  "size": "medium", "sparse": false},
    {"name": "kddcup09appetency",         "id": 2,  "size": "medium", "sparse": false},
    {"name": "yeast",                     "id": 3,  "size": "small",  "sparse": false},
    {"name": "waveform",                  "id": 4,  "size": "small",  "sparse": false},
    {"name": "cifar10small",              "id": 5,  "size": "large",  "sparse": false},
    {"name": "mnistrotationbackimagenew", "id": 0,  "size": "large",  "sparse": false},
    {"name": "krvskp",                    "id": 6,  "size": "small",  "sparse": false},
    {"name": "car",                       "id": 7,  "size": "small",  "sparse": false},
    {"name": "madelon",                   "id": 8,  "size": "medium", "sparse": false},
    {"name": "abalone",                   "id": 9,  "size": "small",  "sparse": false},
    {"name": "mnist",                     "id": 10, "size": "large",  "sparse": false},
    {"name": "dexter",                    "id": 11, "size": "small",  "sparse": true},
    {"name": "amazon",                    "id": 12, "size": "medium", "sparse": false},
    {"name": "cifar10",                   "id": 13, "size": "large",  "sparse": false},
    {"name": "germancredit",              "id": 14, "size": "small",  "sparse": false},
    {"name": "gisette",                   "id": 15, "size": "large",  "sparse": false},
    {"name": "convex",                    "id": 16, "size": "large",  "sparse": false},
    {"name": "winequalitywhite",          "id": 17, "size": "small",  "sparse": false},
    {"name": "shuttle",                   "id": 18, "size": "small",  "sparse": false},
    {"name": "semeion",                   "id": 19, "size": "small",  "sparse": false}
]
